[
    {
        "class": "my-0",
        "sass": "@include my('0')",
        "property": "margin-top: 0, margin-bottom: 0",
        "px" : ""
    },
    {
        "class": "my-px",
        "sass": "@include my('px')",
        "property": "margin-top: 1px, margin-bottom: 1px",
        "px" : ""
    },
    {
        "class": "my-2",
        "sass": "@include my('2')",
        "property": "margin-top: 0.125rem, margin-bottom: 0.125rem",
        "px" : "/* 2px */"
    },
    {
        "class": "my-4",
        "sass": "@include my('4')",
        "property": "margin-top: 0.25rem, margin-bottom: 0.25rem",
        "px" : "/* 4px */"
    },
    {
        "class": "my-6",
        "sass": "@include my('6')",
        "property": "margin-top: 0.375rem, margin-bottom: 0.375rem",
        "px" : "/* 6px */"
    },
    {
        "class": "my-8",
        "sass": "@include my('8')",
        "property": "margin-top: 0.5rem, margin-bottom: 0.5rem",
        "px" : "/* 8px */"
    },
    {
        "class": "my-10",
        "sass": "@include my('10')",
        "property": "margin-top: 0.625rem, margin-bottom: 0.625rem",
        "px" : "/* 10px */"
    },
    {
        "class": "my-12",
        "sass": "@include my('12')",
        "property": "margin-top: 0.75rem, margin-bottom: 0.75rem",
        "px" : "/* 12px */"
    },
    {
        "class": "my-14",
        "sass": "@include my('14')",
        "property": "margin-top: 0.875rem, margin-bottom: 0.875rem",
        "px" : "/* 14px */"
    },
    {
        "class": "my-16",
        "sass": "@include my('16')",
        "property": "margin-top: 1rem, margin-bottom: 1rem",
        "px" : "/* 16px */"
    },
    {
        "class": "my-18",
        "sass": "@include my('18')",
        "property": "margin-top: 1.125rem, margin-bottom: 1.125rem",
        "px" : "/* 18px */"
    },
    {
        "class": "my-20",
        "sass": "@include my('20')",
        "property": "margin-top: 1.25rem, margin-bottom: 1.25rem",
        "px" : "/* 20px */"
    },
    {
        "class": "my-24",
        "sass": "@include my('24')",
        "property": "margin-top: 1.5rem, margin-bottom: 1.5rem",
        "px" : "/* 24px */"
    },
    {
        "class": "my-28",
        "sass": "@include my('28')",
        "property": "margin-top: 1.75rem, margin-bottom: 1.75rem",
        "px" : "/* 28px */"
    },
    {
        "class": "my-30",
        "sass": "@include my('30')",
        "property": "margin-top: 1.875rem, margin-bottom: 1.875rem",
        "px" : "/* 30px */"
    },
    {
        "class": "my-32",
        "sass": "@include my('32')",
        "property": "margin-top: 2rem, margin-bottom: 2rem",
        "px" : "/* 32px */"
    },
    {
        "class": "my-34",
        "sass": "@include my('34')",
        "property": "margin-top: 2.125rem, margin-bottom: 2.125rem",
        "px" : "/* 34px */"
    },
    {
        "class": "my-36",
        "sass": "@include my('36')",
        "property": "margin-top: 2.25rem, margin-bottom: 2.25rem",
        "px" : "/* 36px */"
    },
    {
        "class": "my-40",
        "sass": "@include my('40')",
        "property": "margin-top: 2.5rem, margin-bottom: 2.5rem",
        "px" : "/* 40px */"
    },
    {
        "class": "my-44",
        "sass": "@include my('44')",
        "property": "margin-top: 2.75rem, margin-bottom: 2.75rem",
        "px" : "/* 44px */"
    },
    {
        "class": "my-xxs",
        "sass": "@include my('xxs')",
        "property": "margin-top: 0.25rem, margin-bottom: 0.25rem",
        "px" : "/* 4px */"
    },
    {
        "class": "my-xs",
        "sass": "@include my('xs')",
        "property": "margin-top: 0.5rem, margin-bottom: 0.5rem",
        "px" : "/* 8px */"
    },
    {
        "class": "my-sm",
        "sass": "@include my('sm')",
        "property": "margin-top: 1rem, margin-bottom: 1rem",
        "px" : "/* 16px */"
    },
    {
        "class": "my-md",
        "sass": "@include my('md')",
        "property": "margin-top: 1.5rem, margin-bottom: 1.5rem",
        "px" : "/* 24px */"
    },
    {
        "class": "my-lg",
        "sass": "@include my('lg')",
        "property": "margin-top: 2rem, margin-bottom: 2rem",
        "px" : "/* 32px */"
    },
    {
        "class": "my-xl",
        "sass": "@include my('xl')",
        "property": "margin-top: 3rem, margin-bottom: 3rem",
        "px" : "/* 48px */"
    },
    {
        "class": "my-2xl",
        "sass": "@include my('2xl')",
        "property": "margin-top: 4rem, margin-bottom: 4rem",
        "px" : "/* 64px */"
    },
    {
        "class": "my-3xl",
        "sass": "@include my('3xl')",
        "property": "margin-top: 5rem, margin-bottom: 5rem",
        "px" : "/* 80px */"
    },
    {
        "class": "my-4xl",
        "sass": "@include my('4xl')",
        "property": "margin-top: 6rem, margin-bottom: 6rem",
        "px" : "/* 96px */"
    },
    {
        "class": "my-5xl",
        "sass": "@include my('5xl')",
        "property": "margin-top: 7rem, margin-bottom: 7rem",
        "px" : "/* 112px */"
    },
    {
        "class": "my-6xl",
        "sass": "@include my('6xl')",
        "property": "margin-top: 8rem, margin-bottom: 8rem",
        "px" : "/* 128px */"
    },
    {
        "class": "my-7xl",
        "sass": "@include my('7xl')",
        "property": "margin-top: 9rem, margin-bottom: 9rem",
        "px" : "/* 144px */"
    },
    {
        "class": "my-8xl",
        "sass": "@include my('8xl')",
        "property": "margin-top: 10rem, margin-bottom: 10rem",
        "px" : "/* 160px */"
    },
    {
        "class": "my-9xl",
        "sass": "@include my('9xl')",
        "property": "margin-top: 11rem, margin-bottom: 11rem",
        "px" : "/* 176px */"
    },
    {
        "class": "my-10xl",
        "sass": "@include my('10xl')",
        "property": "margin-top: 12rem, margin-bottom: 12rem",
        "px" : "/* 192px */"
    },
    {
        "class": "my-vh",
        "sass": "@include my('vh')",
        "property": "margin-top: 100vh, margin-bottom: 100vh",
        "px" : ""
    },
    {
        "class": "my-vw",
        "sass": "@include my('vw')",
        "property": "margin-top: 100vw, margin-bottom: 100vw",
        "px" : ""
    },
    {
        "class": "my-full",
        "sass": "@include my('full')",
        "property": "margin-top: 100%, margin-bottom: 100%",
        "px" : ""
    },
    {
        "class": "my-auto",
        "sass": "@include my('auto')",
        "property": "margin-top: auto, margin-bottom: auto",
        "px" : ""
    }


]